j2/__init__.py
j2/cli.py
j2/config.py
j2/constant.py
j2/markdown_environment.py
j2/markdown_file_system_loader.py
make_ninja_build/__init__.py
make_ninja_build/cli.py
make_ninja_build/ninja_build_generator.py
md_cp/__init__.py
md_cp/cli.py
md_render/__init__.py
md_render/cli.py
md_render/work_dir_context.py
share/render_helper.py
share/utils.py
md_cli-1.0.1.dist-info/METADATA
md_cli-1.0.1.dist-info/WHEEL
md_cli-1.0.1.dist-info/entry_points.txt
md_cli-1.0.1.dist-info/top_level.txt
md_cli-1.0.1.dist-info/RECORD
