Metadata-Version: 2.4
Name: md_cli
Version: 1.0.1
Summary: Markdown Jinja2 command line tools
Author-email: Bryt <bryt.xin.li@gmail.com>
Project-URL: Homepage, https://github.com/xin-at-marathon/pypi/md_cli/
Project-URL: Issues, https://github.com/xin-at-marathon/pypi/issues
Classifier: Programming Language :: Python :: 3
Classifier: License :: OSI Approved :: MIT License
Classifier: Operating System :: OS Independent
Requires-Python: >=3.6
Requires-Dist: jinja2
Requires-Dist: PyYAML
Requires-Dist: python-dotenv
Requires-Dist: ninja
Requires-Dist: ninja_syntax
